brokerlso/__init__.py
brokerlso/qmfv2.py
brokerlso-0.0.2.data/data/usr/share/doc/brokerlso/about.html
brokerlso-0.0.2.data/data/usr/share/doc/brokerlso/brokerlso.html
brokerlso-0.0.2.data/data/usr/share/doc/brokerlso/genindex.html
brokerlso-0.0.2.data/data/usr/share/doc/brokerlso/index.html
brokerlso-0.0.2.data/data/usr/share/doc/brokerlso/modules.html
brokerlso-0.0.2.data/data/usr/share/doc/brokerlso/objects.inv
brokerlso-0.0.2.data/data/usr/share/doc/brokerlso/py-modindex.html
brokerlso-0.0.2.data/data/usr/share/doc/brokerlso/search.html
brokerlso-0.0.2.data/data/usr/share/doc/brokerlso/searchindex.js
brokerlso-0.0.2.data/data/usr/share/doc/brokerlso/_sources/about.txt
brokerlso-0.0.2.data/data/usr/share/doc/brokerlso/_sources/brokerlso.txt
brokerlso-0.0.2.data/data/usr/share/doc/brokerlso/_sources/index.txt
brokerlso-0.0.2.data/data/usr/share/doc/brokerlso/_sources/modules.txt
brokerlso-0.0.2.data/data/usr/share/doc/brokerlso/_static/ajax-loader.gif
brokerlso-0.0.2.data/data/usr/share/doc/brokerlso/_static/alabaster.css
brokerlso-0.0.2.data/data/usr/share/doc/brokerlso/_static/basic.css
brokerlso-0.0.2.data/data/usr/share/doc/brokerlso/_static/comment-bright.png
brokerlso-0.0.2.data/data/usr/share/doc/brokerlso/_static/comment-close.png
brokerlso-0.0.2.data/data/usr/share/doc/brokerlso/_static/comment.png
brokerlso-0.0.2.data/data/usr/share/doc/brokerlso/_static/custom.css
brokerlso-0.0.2.data/data/usr/share/doc/brokerlso/_static/doctools.js
brokerlso-0.0.2.data/data/usr/share/doc/brokerlso/_static/down-pressed.png
brokerlso-0.0.2.data/data/usr/share/doc/brokerlso/_static/down.png
brokerlso-0.0.2.data/data/usr/share/doc/brokerlso/_static/file.png
brokerlso-0.0.2.data/data/usr/share/doc/brokerlso/_static/jquery-1.11.1.js
brokerlso-0.0.2.data/data/usr/share/doc/brokerlso/_static/jquery.js
brokerlso-0.0.2.data/data/usr/share/doc/brokerlso/_static/minus.png
brokerlso-0.0.2.data/data/usr/share/doc/brokerlso/_static/plus.png
brokerlso-0.0.2.dist-info/DESCRIPTION.rst
brokerlso-0.0.2.dist-info/METADATA
brokerlso-0.0.2.dist-info/RECORD
brokerlso-0.0.2.dist-info/WHEEL
brokerlso-0.0.2.dist-info/metadata.json
brokerlso-0.0.2.dist-info/top_level.txt
